{
  "parent": "minecraft:recipes/root",
  "criteria": {
    "has_ridge_pine_stripped_wood": {
      "conditions": {
        "items": [
          {
            "items": "eden_realm:ridge_pine_stripped_wood"
          }
        ]
      },
      "trigger": "minecraft:inventory_changed"
    },
    "has_the_recipe": {
      "conditions": {
        "recipe": "eden_realm:ridge_pine_planks_from_stripped_wood"
      },
      "trigger": "minecraft:recipe_unlocked"
    }
  },
  "requirements": [
    [
      "has_the_recipe",
      "has_ridge_pine_stripped_wood"
    ]
  ],
  "rewards": {
    "recipes": [
      "eden_realm:ridge_pine_planks_from_stripped_wood"
    ]
  }
}